<?xml version='1.0' encoding='utf-8'?>
<container xmlns="https://open.law/schemas/library" xmlns:cache="https://open.law/schemas/cache" xmlns:citations="https://open.law/schemas/citations" xmlns:macro="https://open.law/schemas/macro" xmlns:xs="http://www.w3.org/2001/XMLSchema" xmlns:xsl="http://www.w3.org/1999/XSL/Transform" xmlns:codified="https://open.law/schemas/codified" xmlns:codify="https://open.law/schemas/codify" xmlns:xi="http://www.w3.org/2001/XInclude">
  <prefix>Chapter</prefix>
  <num>14</num>
  <heading>Video Lottery Facility Minimum Internal Control Standards</heading>
  <reason>Repealed</reason>
  <annotations>
    <annotation type="History" dest="container" effective="2010-08-23">Effective date: August 23, 2010 (37:17 Md. R. 1186)</annotation>
    <annotation type="History" dest="container" effective="2012-12-24">Regulation .04C amended effective December 24, 2012 (39:25 Md. R. 1615)</annotation>
    <annotation type="History" dest="container" effective="2011-06-27">Regulation .05A amended effective June 27, 2011 (38:13 Md. R. 756)</annotation>
    <annotation type="History" dest="container" effective="2012-12-24">Regulation .08F amended effective December 24, 2012 (39:25 Md. R. 1615)</annotation>
    <annotation type="History" dest="container" effective="2010-12-27">Regulation .16B amended as an emergency provision effective October 13, 2010 (37:23 Md. R. 1607); amended permanently effective December 27, 2010 (37:26 Md. R. 1789)</annotation>
    <annotation type="History" dest="container" effective="2012-04-16">Regulation .17 amended effective April 16, 2012 (39:7 Md. R. 495)</annotation>
    <annotation type="History" dest="container" effective="2010-12-27">Regulation .20I amended as an emergency provision effective October 13, 2010 (37:23 Md. R. 1607); amended permanently effective December 27, 2010 (37:26 Md. R. 1789)</annotation>
    <annotation type="History" dest="container" effective="2010-12-27">Regulation .36B amended as an emergency provision effective October 13, 2010 (37:23 Md. R. 1607); amended permanently effective December 27, 2010 (37:26 Md. R. 1789)</annotation>
    <annotation type="History" dest="container" effective="2012-12-24">Regulation .37A,D,E amended effective December 24, 2012 (39:25 Md. R. 1615)</annotation>
    <annotation type="History" dest="container" effective="2012-05-28">Regulation .37B amended effective May 28, 2012 (39:10 Md. R. 661)</annotation>
    <annotation type="History" dest="container" effective="2012-05-28">Regulation .37F—H adopted effective May 28, 2012 (39:10 Md. R. 661)</annotation>
    <annotation type="History" dest="container" effective="2012-12-24">Regulation .38C, E amended effective December 24, 2012 (39:25 Md. R. 1615)</annotation>
    <annotation type="History" dest="container" effective="2011-01-24">Regulation .44 amended as an emergency provision effective October 13, 2010 (37:23 Md. R. 1607); amended permanently effective January 24, 2011 (38:2 Md. R. 84)</annotation>
    <annotation type="History" dest="container" effective="2012-12-24">Regulation .45B amended effective December 24, 2012 (39:25 Md. R. 1615)</annotation>
    <annotation type="History" dest="container" effective="2010-12-27">Regulation .46 amended as an emergency provision effective October 13, 2010 (37:23 Md. R. 1607); amended permanently effective December 27, 2010 (37:26 Md. R. 1789)</annotation>
    <annotation type="History" dest="container" effective="2012-04-16">Regulation .47B, C amended effective April 16, 2012 (39:7 Md. R. 495)</annotation>
    <annotation type="History" dest="container" effective="2012-12-24">Regulation .50 adopted effective December 24, 2012 (39:25 Md. R. 1615)</annotation>
    <annotation type="History" dest="container" discontinuity="true" effective="2013-03-01">Chapter repealed as an emergency provision effective March 1, 2013 (40:7 Md. R. 608)</annotation>
  </annotations>
</container>
