<?xml version='1.0' encoding='utf-8'?>
<container xmlns="https://open.law/schemas/library" xmlns:cache="https://open.law/schemas/cache" xmlns:citations="https://open.law/schemas/citations" xmlns:macro="https://open.law/schemas/macro" xmlns:xs="http://www.w3.org/2001/XMLSchema" xmlns:xsl="http://www.w3.org/1999/XSL/Transform" xmlns:codified="https://open.law/schemas/codified" xmlns:codify="https://open.law/schemas/codify" xmlns:xi="http://www.w3.org/2001/XInclude">
  <prefix>Chapter</prefix>
  <num>65</num>
  <heading>Maryland Medicaid Managed Care Program: Managed Care Organizations — Transferred to COMAR 10.67.04</heading>
  <annotations>
    <annotation type="History" dest="container">Effective date:</annotation>
    <annotation type="History" dest="container" effective="1996-11-08">Regulations .01—.23 adopted as an emergency provision effective November 8, 1996 (23:25 Md. R. 1730)</annotation>
    <annotation type="History" dest="container" effective="1997-03-10">Regulations .01—.23 adopted effective March 10, 1997 (24:5 Md. R. 408)</annotation>
    <annotation type="History" dest="container" effective="2002-10-28">Regulation .01 amended as an emergency provision effective July 1, 2002 (29:15 Md. R. 1139); amended permanently effective October 28, 2002 (29:21 Md. R. 1645)</annotation>
    <annotation type="History" dest="container" effective="1997-07-01">Regulations .02C, .04C, .08, .11, .15, .17A, .18, .20B, and .22C amended and Regulation .11-1 adopted as an emergency provision effective July 1, 1997 (24:16 Md. R. 1151); emergency status expired December 31, 1997</annotation>
    <annotation type="History" dest="container" effective="2002-02-18">Regulation .02 amended effective February 9, 1998 (25:3 Md. R. 144); November 1, 1999 (26:22 Md. R. 1692); February 18, 2002 (29:3 Md. R.220)</annotation>
    <annotation type="History" dest="container" effective="2002-10-28">Regulation .02 amended as an emergency provision effective July 1, 2002 (29:15 Md. R. 1139); amended permanently effective October 28, 2002 (29:21 Md. R. 1645)</annotation>
    <annotation type="History" dest="container" effective="2002-12-23">Regulation .02 amended effective December 23, 2002 (29:25 Md. R. 1981)</annotation>
    <annotation type="History" dest="container" effective="1999-01-01">Regulation .02G amended as an emergency provision effective July 1, 1998 (25:16 Md. R. 1261); adopted permanently effective January 1, 1999 (25:26 Md. R. 1925)</annotation>
    <annotation type="History" dest="container" effective="2003-11-10">Regulation .02G and H amended as an emergency provision effective July 1, 2003 (30:21 Md. R. 1527); amended permanently effective November 10, 2003 (30:22 Md. R. 1580)</annotation>
    <annotation type="History" dest="container" effective="1999-01-01">Regulation .03P amended as an emergency provision effective July 1, 1998 (25:16 Md. R. 1261); adopted permanently effective January 1, 1999 (25:26 Md. R. 1925)</annotation>
    <annotation type="History" dest="container" effective="2002-02-18">Regulation .03T adopted effective February 18, 2002 (29:3 Md. R.220)</annotation>
    <annotation type="History" dest="container" effective="2002-12-23">Regulation .03 repealed and new Regulation .03 adopted effective December 23, 2002 (29:25 Md. R. 1981)</annotation>
    <annotation type="History" dest="container" effective="1998-02-09">Regulation .04C amended effective February 9, 1998 (25:3 Md. R. 144)</annotation>
    <annotation type="History" dest="container" effective="1999-01-01">Regulation .05 amended as an emergency provision effective July 1, 1998 (25:16 Md. R. 1261); adopted permanently effective January 1, 1999 (25:26 Md. R. 1925)</annotation>
    <annotation type="History" dest="container" effective="2002-10-28">Regulation .05 amended as an emergency provision effective July 1, 2002 (29:15 Md. R. 1139); amended permanently effective October 28, 2002 (29:21 Md. R. 1645)</annotation>
    <annotation type="History" dest="container" effective="2002-12-23">Regulation .05K amended effective December 23, 2002 (29:25 Md. R. 1981)</annotation>
    <annotation type="History" dest="container" effective="1998-02-09">Regulation .08 amended effective February 9, 1998 (25:3 Md. R. 144)</annotation>
    <annotation type="History" dest="container" effective="1999-01-01">Regulation .08 amended as an emergency provision effective July 1, 1998 (25:16 Md. R. 1261); adopted permanently effective January 1, 1999 (25:26 Md. R. 1925)</annotation>
    <annotation type="History" dest="container" effective="2002-02-18">Regulation .10B amended effective February 18, 2002 (29:3 Md. R.220)</annotation>
    <annotation type="History" dest="container" effective="1998-02-09">Regulation .11 amended effective February 9, 1998 (25:3 Md. R. 144)</annotation>
    <annotation type="History" dest="container" effective="1999-01-01">Regulation .11 amended as an emergency provision effective July 1, 1998 (25:16 Md. R. 1261); adopted permanently effective January 1, 1999 (25:26 Md. R. 1925)</annotation>
    <annotation type="History" dest="container" effective="2000-10-16">Regulation .11 amended as an emergency provision effective July 1, 2000 (27:15 Md. R. 1397); amended permanently effective October 16, 2000 (27:20 Md. 1838)</annotation>
    <annotation type="History" dest="container" effective="2002-12-23">Regulation .11 amended effective February 18, 2002 (29:3 Md. R.220); December 23, 2002 (29:25 Md. R. 1981)</annotation>
    <annotation type="History" dest="container" effective="1998-02-09">Regulation .11-1 and .11-2 adopted February 9, 1998 (25:3 Md. R. 144)</annotation>
    <annotation type="History" dest="container" effective="1999-01-01">Regulation .11-1 and .11-2E amended as an emergency provision effective July 1, 1998 (25:16 Md. R. 1261); adopted permanently effective January 1, 1999 (25:26 Md. R. 1925)</annotation>
    <annotation type="History" dest="container" effective="2000-10-16">Regulations .11-1 and .11-2 amended as an emergency provision effective July 1, 2000 (27:15 Md. R. 1397); amended permanently effective October 16, 2000 (27:20 Md. R. 1838)</annotation>
    <annotation type="History" dest="container" effective="2002-02-18">Regulation .15 amended effective February 9, 1998 (25:3 Md. R. 144); December 25, 2000 (27:25 Md. R. 2281); February 18, 2002 (29:3 Md. R.220)</annotation>
    <annotation type="History" dest="container" effective="1999-01-01">Regulation .15B amended as an emergency provision effective July 1, 1998 (25:16 Md. R. 1261); adopted permanently effective January 1, 1999 (25:26 Md. R. 1925)</annotation>
    <annotation type="History" dest="container" effective="2002-10-28">Regulation .15D, E amended as an emergency provision effective July 1, 2002 (29:15 Md. R. 1139); amended permanently effective October 28, 2002 (29:21 Md. R. 1645)</annotation>
    <annotation type="History" dest="container" effective="1999-01-01">Regulation .16 amended as an emergency provision effective July 1, 1998 (25:16 Md. R. 1261); adopted permanently effective January 1, 1999 (25:26 Md. R. 1925)</annotation>
    <annotation type="History" dest="container" effective="2002-12-23">Regulation .17A amended effective February 9, 1998 (25:3 Md. R. 144); December 23, 2002 (29:25 Md. R. 1981)</annotation>
    <annotation type="History" dest="container" effective="2002-02-18">Regulation .17B amended effective February 18, 2002 (29:3 Md. R.220)</annotation>
    <annotation type="History" dest="container" effective="1998-02-09">Regulation .18 amended effective February 9, 1998 (25:3 Md. R. 144)</annotation>
    <annotation type="History" dest="container" effective="1998-06-29">Regulation .18-1 adopted as an emergency provision effective April 7, 1998 (25:9 Md. R. 676); adopted permanently effective June 29, 1998 (25:13 Md. R. 993)</annotation>
    <annotation type="History" dest="container" effective="2000-12-25">Regulation .18-1 amended effective December 25, 2000 (27:25 Md. R.2281)</annotation>
    <annotation type="History" dest="container" effective="1999-11-01">Regulation .18-1C adopted effective November 1, 1999 (26:22 Md. R. 1692)</annotation>
    <annotation type="History" dest="container" effective="1998-07-01">Regulation .19 amended as an emergency provision effective July 1, 1998 (25:16 Md. R. 1261); emergency status extended at 26:1 Md. R. 17, 26:6 Md. R. 480, and 26:8 Md. R. 614; emergency status expired May 1, 1999</annotation>
    <annotation type="History" dest="container" effective="1999-05-01">Regulation .19 amended as an emergency provision effective May 1, 1999 (26:9 Md. R. 727 and 26:10 Md. R. 794); emergency status expired November 1, 1999</annotation>
    <annotation type="History" dest="container" effective="1999-11-01">Regulation .19 amended effective November 1, 1999 (26:22 Md. R. 1692)</annotation>
    <annotation type="History" dest="container" effective="1999-12-01">Regulation .19 amended as an emergency provision effective December 1, 1999 (26:25 Md. R. 1888); emergency status expired December 25, 2000</annotation>
    <annotation type="History" dest="container" effective="2000-12-25">Regulation .19 amended effective December 25, 2000 (27:25 Md. R.2281)</annotation>
    <annotation type="History" dest="container" effective="2002-12-23">Regulation .19 amended effective December 23, 2002 (29:25 Md. R. 1981)</annotation>
    <annotation type="History" dest="container" effective="2001-03-31">Regulation .19A amended as an emergency provision effective March 31, 2001 (28:7 Md. R. 685); emergency status extended at 28:22 Md. R. 1931 and 29:4 Md. R. 413</annotation>
    <annotation type="History" dest="container" effective="2001-12-24">Regulation .19B amended effective December 24, 2001 (28:25 Md. R. 2190)</annotation>
    <annotation type="History" dest="container" effective="2002-10-28">Regulation .19B amended as an emergency provision effective July 1, 2002 (29:15 Md. R. 1139); amended permanently effective October 28, 2002 (29:21 Md. R. 1645)</annotation>
    <annotation type="History" dest="container" effective="2003-11-10">Regulation .19D amended as an emergency provision effective July 1, 2003 (30:21 Md. R. 1527); amended permanently effective November 10, 2003 (30:22 Md. R. 1580)</annotation>
    <annotation type="History" dest="container" effective="1999-12-01">Regulations .19-1—.19-3 adopted as an emergency provision effective December 1, 1999 (26:25 Md. R. 1888); emergency status expired December 25, 2000</annotation>
    <annotation type="History" dest="container" effective="2000-12-25">Regulations .19-1—.19-4 adopted effective December 25, 2000 (27:25 Md. R. 2281)</annotation>
    <annotation type="History" dest="container" effective="2001-12-24">Regulations .19-1 and .19-2 repealed and new Regulation .19-1 adopted effective December 24, 2001 (28:25 Md. R. 2190)</annotation>
    <annotation type="History" dest="container" effective="2003-11-10">Regulation .19-1 repealed as an emergency provision effective July 1, 2003 (30:21 Md. R. 1527); repealed permanently effective November 10, 2003 (30:22 Md. R. 1580)</annotation>
    <annotation type="History" dest="container" effective="2001-12-24">Regulations .19-3 and .19-4 amended and recodified to be new Regulations .19-2 and .19-3 effective December 24, 2001 (28:25 Md. R. 2190)</annotation>
    <annotation type="History" dest="container" effective="2002-10-28">Regulation .19-3 amended as an emergency provision effective July 1, 2002 (29:15 Md. R. 1139); amended permanently effective October 28, 2002 (29:21 Md. R. 1645)</annotation>
    <annotation type="History" dest="container" effective="2002-12-23">Regulation .19-3 amended effective December 23, 2002 (29:25 Md. R. 1981)</annotation>
    <annotation type="History" dest="container" effective="2002-12-23">Regulation .19-4 adopted effective December 23, 2002 (29:25 Md. R. 1981)</annotation>
    <annotation type="History" dest="container" effective="2001-03-31">Regulations .19-5 and.19-6 adopted as an emergency provision effective March 31, 2001 (28:7 Md. R. 685); emergency status extended at 28:22 Md. R. 1931; emergency status extended at 29:4 Md. R. 413</annotation>
    <annotation type="History" dest="container" effective="1999-01-01">Regulation .20 amended as an emergency provision effective July 1, 1998 (25:16 Md. R. 1261); amended permanently effective January 1, 1999 (25:26 Md. R. 1925)</annotation>
    <annotation type="History" dest="container" effective="2003-11-10">Regulation .20 amended as an emergency provision effective July 1, 2003 (30:21 Md. R. 1527); amended permanently effective November 10, 2003 (30:22 Md. R. 1580)</annotation>
    <annotation type="History" dest="container" effective="2002-12-23">Regulation .20A amended effective December 23, 2002 (29:25 Md. R. 1981)</annotation>
    <annotation type="History" dest="container" effective="1998-02-09">Regulation .20B amended effective February 9, 1998 (25:3 Md. R. 144)</annotation>
    <annotation type="History" dest="container" effective="2003-07-07">Regulation .21 amended effective December 25, 2000 (27:25 Md. R. 2281); December 24, 2001 (28:25 Md. R. 2190); July 7, 2003 (30:13 Md. R. 854)</annotation>
    <annotation type="History" dest="container" effective="1999-05-01">Regulation .22 amended as an emergency provision effective May 1, 1999 (26:9 Md. R. 727 and 26:10 Md. R. 794); emergency status expired November 1, 1999</annotation>
    <annotation type="History" dest="container" effective="1999-12-01">Regulation .22 amended as an emergency provision effective December 1, 1999 (26:25 Md. R. 1888); emergency status expired December 25, 2000</annotation>
    <annotation type="History" dest="container" effective="2001-06-25">Regulation .22 amended as an emergency provision effective December 1, 2000 (27:26 Md. R. 2355); emergency status extended at 28:7 Md. R. 685; adopted permanently effective June 25, 2001 (28:12 Md. R. 1109)</annotation>
    <annotation type="History" dest="container" effective="2001-12-24">Regulation .22 amended effective December 24, 2001 (28:25 Md. R. 2190)</annotation>
    <annotation type="History" dest="container" effective="1999-11-01">Regulation .22A amended and F—J adopted effective November 1, 1999 (26:22 Md. R. 1692)</annotation>
    <annotation type="History" dest="container" effective="1998-02-09">Regulation .22C amended effective February 9, 1998 (25:3 Md. R. 144)</annotation>
    <annotation type="History" dest="container" effective="1999-01-01">Regulations .24 and .25 adopted as an emergency provision effective July 1, 1998 (25:16 Md. R. 1261); adopted permanently effective January 1, 1999 (25:26 Md. R. 1925)</annotation>
    <annotation type="History" dest="container" effective="1999-12-01">Regulation .24 amended as an emergency provision effective December 1, 1999 (26:25 Md. R. 1888); emergency status expired December 25, 2000</annotation>
    <annotation type="History" dest="container" effective="2002-12-23">Regulation .24 amended effective December 25, 2000 (27:25 Md. R.2281); December 23, 2002 (29:25 Md. R. 1981)</annotation>
    <annotation type="History" dest="container" effective="1999-12-01">Regulation .24-1 adopted as an emergency provision effective December 1, 1999 (26:25 Md. R. 1888); emergency status expired December 31, 2000</annotation>
    <annotation type="History" dest="container" effective="2002-02-18">Regulation .26 adopted effective February 18, 2002 (29:3 Md. R. 220)</annotation>
    <annotation type="History" dest="container" effective="2002-02-18">Regulation .27 adopted effective February 18, 2002 (29:3 Md. R. 220)</annotation>
    <annotation type="History" dest="container" discontinuity="true" effective="2004-02-02">Chapter revised effective February 2, 2004 (31:2 Md. R. 82)</annotation>
    <annotation type="History" dest="container" effective="2015-02-16">Regulation .01 repealed effective February 16, 2015 (42:3 Md. R. 316)</annotation>
    <annotation type="History" dest="container" effective="2010-12-27">Regulation .01B amended effective December 27, 2010 (37:26 Md. R. 1787)</annotation>
    <annotation type="History" dest="container" effective="2018-02-26">Regulation .02 amended effective June 30, 2008 (35:13 Md. R. 1180); April 28, 2014 (41:8 Md. R. 471); February 16, 2015 (42:3 Md. R. 316); February 26, 2018 (45:4 Md. R. 205)</annotation>
    <annotation type="History" dest="container" effective="2005-04-11">Regulation .02G amended as an emergency provision effective January 5, 2005 (32:6 Md. R. 634); amended permanently effective April 11, 2005 (32:7 Md. R. 679)</annotation>
    <annotation type="History" dest="container" effective="2016-11-07">Regulation .02G, J, X amended effective November 7, 2016 (43:22 Md. R. 1221)</annotation>
    <annotation type="History" dest="container" effective="2012-12-24">Regulation .02K amended effective December 24, 2012 (39:25 Md. R. 1613)</annotation>
    <annotation type="History" dest="container" effective="2009-02-23">Regulation .02O, S amended as an emergency provision effective November 1, 2008 (35:24 Md. R. 2069); amended permanently effective February 23, 2009 (36:4 Md. R. 353)</annotation>
    <annotation type="History" dest="container" effective="2010-12-27">Regulation .02V amended effective December 27, 2010 (37:26 Md. R. 1787)</annotation>
    <annotation type="History" dest="container" effective="2007-11-05">Regulation .02Z adopted effective November 5, 2007 (34:22 Md. R. 1977)</annotation>
    <annotation type="History" dest="container" effective="2016-03-14">Regulation .02CC amended effective October 5, 2009 (36:20 Md. R. 1528); March 14, 2016 (43:5 Md. R. 385)</annotation>
    <annotation type="History" dest="container" effective="2012-02-06">Regulation .02DD adopted effective February 6, 2012 (39:2 Md. R. 141)</annotation>
    <annotation type="History" dest="container" effective="2012-12-24">Regulation .02EE adopted effective December 24, 2012 (39:25 Md. R. 1613)</annotation>
    <annotation type="History" dest="container" effective="2013-10-28">Regulation .02K, L amended effective October 28, 2013 (40:21 Md. R. 1775)</annotation>
    <annotation type="History" dest="container" effective="2013-10-28">Regulation .02FF adopted effective October 28, 2013 (40:21 Md. R. 1775)</annotation>
    <annotation type="History" dest="container" effective="2018-02-12">Regulation .03 amended effective February 12, 2018 (45:3 Md. R. 156)</annotation>
    <annotation type="History" dest="container" effective="2015-10-26">Regulation .03A, B amended effective October 26, 2015 (42:21 Md. R. 1301)</annotation>
    <annotation type="History" dest="container" effective="2008-06-30">Regulation .03B amended effective December 19, 2005 (32:25 Md. R. 1941); April 9, 2007 (34:7 Md. R. 698); November 5, 2007 (34:22 Md. R. 1977); June 30, 2008 (35:13 Md. R. 1180)</annotation>
    <annotation type="History" dest="container" effective="2009-02-23">Regulation .03B amended as an emergency provision effective November 1, 2008 (35:24 Md. R. 2069); amended permanently effective February 23, 2009 (36:4 Md. R. 353)</annotation>
    <annotation type="History" dest="container" effective="2018-12-31">Regulation .03B amended effective October 5, 2009 (36:20 Md. R. 1528); April 19, 2010 (37:8 Md. R. 615); December 27, 2010 (37:26 Md. R. 1787); February 6, 2012 (39:2 Md. R. 141); December 24, 2012 (39:25 Md. R. 1613); December 12, 2013 (40:24 Md. R. 2017); August 29, 2016 (43:17 Md. R. 955); November 7, 2016 (43:22 Md. R. 1221); December 31, 2018 (45:26 Md. R. 1245)</annotation>
    <annotation type="History" dest="container" effective="2015-02-16">Regulation .04B amended effective April 10, 2006 (33:7 Md. R. 668); February 16, 2015 (42:3 Md. R. 316)</annotation>
    <annotation type="History" dest="container" effective="2018-02-26">Regulation .04C amended effective June 30, 2008 (35:13 Md. R. 1180); February 26, 2018 (45:4 Md. R. 205)</annotation>
    <annotation type="History" dest="container" effective="2009-02-23">Regulation .05I amended as an emergency provision effective November 1, 2008 (35:24 Md. R. 2069); amended permanently effective February 23, 2009 (36:4 Md. R. 353)</annotation>
    <annotation type="History" dest="container" effective="2015-02-16">Regulation .05G amended effective February 16, 2015 (42:3 Md. R. 316)</annotation>
    <annotation type="History" dest="container" effective="2018-12-31">Regulation .05K amended effective December 31, 2018 (45:26 Md. R. 1244)</annotation>
    <annotation type="History" dest="container" effective="2006-11-06">Regulation .06C amended effective November 6, 2006 (33:22 Md. R. 1732)</annotation>
    <annotation type="History" dest="container" effective="2014-04-28">Regulation .08 amended effective April 28, 2014 (41:8 Md. R. 471)</annotation>
    <annotation type="History" dest="container" effective="2015-02-16">Regulation .08C, E amended effective February 16, 2015 (42:3 Md. R. 316)</annotation>
    <annotation type="History" dest="container" effective="2012-12-24">Regulation .08I amended effective December 24, 2012 (39:25 Md. R. 1613)</annotation>
    <annotation type="History" dest="container" effective="2006-04-10">Regulation .08K amended effective April 10, 2006 (33:7 Md. R. 668)</annotation>
    <annotation type="History" dest="container" effective="2010-04-19">Regulation .08M repealed effective April 19, 2010 (37:8 Md. R. 615)</annotation>
    <annotation type="History" dest="container" effective="2006-11-06">Regulation .10C amended effective November 6, 2006 (33:22 Md. R. 1732)</annotation>
    <annotation type="History" dest="container" effective="2006-04-10">Regulation .10D amended effective April 10, 2006 (33:7 Md. R. 668)</annotation>
    <annotation type="History" dest="container" effective="2015-02-16">Regulation .10E amended effective February 16, 2015 (42:3 Md. R. 316)</annotation>
    <annotation type="History" dest="container" effective="2005-04-11">Regulation .10F amended as an emergency provision effective January 5, 2005 (32:6 Md. R. 634); amended permanently effective April 11, 2005 (32:7 Md. R. 679)</annotation>
    <annotation type="History" dest="container" effective="2015-02-16">Regulation .11 repealed effective February 16, 2015 (42:3 Md. R. 316)</annotation>
    <annotation type="History" dest="container" effective="2009-10-05">Regulation .11E amended effective October 5, 2009 (36:20 Md. R. 1528)</annotation>
    <annotation type="History" dest="container" effective="2010-04-19">Regulation .11F amended effective April 19, 2010 (37:8 Md. R. 615)</annotation>
    <annotation type="History" dest="container" effective="2009-02-23">Regulation .11G amended as an emergency provision effective November 1, 2008 (35:24 Md. R. 2069); amended permanently effective February 23, 2009 (36:4 Md. R. 353)</annotation>
    <annotation type="History" dest="container" effective="2015-02-16">Regulation .11-1 repealed effective February 16, 2015 (42:3 Md. R. 316)</annotation>
    <annotation type="History" dest="container" effective="2015-02-16">Regulation .11-2 repealed effective February 16, 2015 (42:3 Md. R. 316)</annotation>
    <annotation type="History" dest="container" effective="2015-02-16">Regulation .12B amended effective February 16, 2015 (42:3 Md. R. 316)</annotation>
    <annotation type="History" dest="container" effective="2018-12-31">Regulation .12D repealed effective December 31, 2018 (45:26 Md. R. 1244)</annotation>
    <annotation type="History" dest="container" effective="2012-02-06">Regulation .13F amended effective February 6, 2012 (39:2 Md. R. 141)</annotation>
    <annotation type="History" dest="container" effective="2015-02-16">Regulation .14 amended effective February 16, 2015 (42:3 Md. R. 316)</annotation>
    <annotation type="History" dest="container" effective="2006-11-06">Regulation .14A amended effective November 6, 2006 (33:22 Md. R. 1732)</annotation>
    <annotation type="History" dest="container" effective="2018-12-31">Regulation .15 amended effective February 16, 2015 (42:3 Md. R. 316); February 26, 2018 (45:4 Md. R. 205); December 31, 2018 (45:26 Md. R. 1244)</annotation>
    <annotation type="History" dest="container" effective="2009-02-23">Regulation .15B amended as an emergency provision effective November 1, 2008 (35:24 Md. R. 2069); amended permanently effective February 23, 2009 (36:4 Md. R. 353)</annotation>
    <annotation type="History" dest="container" effective="2007-04-09">Regulation .15C amended effective April 9, 2007 (34:7 Md. R. 698)</annotation>
    <annotation type="History" dest="container" effective="2008-06-30">Regulation .15D amended effective June 30, 2008 (35:13 Md. R. 1180)</annotation>
    <annotation type="History" dest="container" effective="2010-04-19">Regulation .15E amended effective December 19, 2005 (32:25 Md. R. 1941); April 19, 2010 (37:8 Md. R. 615)</annotation>
    <annotation type="History" dest="container" effective="2006-04-10">Regulation .15F amended effective April 10, 2006 (33:7 Md. R. 668)</annotation>
    <annotation type="History" dest="container" effective="2008-06-30">Regulation .15L adopted effective June 30, 2008 (35:13 Md. R. 1180)</annotation>
    <annotation type="History" dest="container" effective="2007-11-05">Regulation .16 repealed effective November 5, 2007 (34:22 Md. R. 1977)</annotation>
    <annotation type="History" dest="container" effective="2018-02-26">Regulation .17 amended effective February 26, 2018 (45:4 Md. R. 205)</annotation>
    <annotation type="History" dest="container" effective="2012-02-06">Regulation .17A amended effective November 6, 2006 (33:22 Md. R. 1732); June 30, 2008 (35:13 Md. R. 1180); February 6, 2012 (39:2 Md. R. 141)</annotation>
    <annotation type="History" dest="container" effective="2016-02-01">Regulation .17B amended effective April 10, 2006 (33:7 Md. R. 668); June 30, 2008 (35:13 Md. R. 1180); October 5, 2009 (36:20 Md. R. 1528); February 1, 2016 (42:23 Md. R. 1434)</annotation>
    <annotation type="History" dest="container" effective="2007-11-05">Regulation .18H amended effective November 5, 2007 (34:22 Md. R. 1977)</annotation>
    <annotation type="History" dest="container" effective="2012-02-06">Regulation .18I, J adopted effective February 6, 2012 (39:2 Md. R. 141)</annotation>
    <annotation type="History" dest="container" effective="2005-01-05">Regulation .19 amended as an emergency provision effective January 5, 2005 (32:6 Md. R. 634)</annotation>
    <annotation type="History" dest="container" effective="2005-07-18">Regulation .19 amended as an emergency provision effective April 1, 2005 (32:9 Md. R. 847); amended permanently effective July 18, 2005 (32:14 Md. R. 1276)</annotation>
    <annotation type="History" dest="container" effective="2013-04-15">Regulation .19 amended effective April 15, 2013 (40:7 Md. R. 611)</annotation>
    <annotation type="History" dest="container" effective="2008-06-16">Regulation .19A, B amended as an emergency provision effective January 1, 2008 (35:3 Md. R. 286); amended permanently effective June 16, 2008 (35:12 Md. R. 1120)</annotation>
    <annotation type="History" dest="container" effective="2018-02-26">Regulation .19A amended effective February 26, 2018 (45:4 Md. R. 205)</annotation>
    <annotation type="History" dest="container" effective="2006-04-10">Regulation .19B amended effective December 20, 2004 (31:25 Md. R.1790); December 19, 2005 (32:25 Md. R. 1941); April 10, 2006 (33:7 Md. R. 669)</annotation>
    <annotation type="History" dest="container" effective="2006-10-23">Regulation .19B amended as an emergency provision effective July 1, 2006 (33:20 Md. R. 1610); amended permanently effective October 23, 2006 (33:21 Md. R. 1675)</annotation>
    <annotation type="History" dest="container" effective="2007-04-09">Regulation .19B amended as an emergency provision effective January 1, 2007 (34:4 Md. R. 396); amended permanently effective April 9, 2007 (34:7 Md. R. 699)</annotation>
    <annotation type="History" dest="container" effective="2007-11-19">Regulation .19B amended as an emergency provision effective September 14, 2007 (34:21 Md. R. 1911); amended permanently effective November 19, 2007 (34:23 Md. R. 2027)</annotation>
    <annotation type="History" dest="container" effective="2019-08-26">Regulation .19B amended effective January 12, 2009 (36:1 Md. R. 21); July 27, 2009 (36:15 Md. R. 1166); January 25, 2010 (37:2 Md. R. 67); June 14, 2010 (37:12 Md. R. 800); December 27, 2010 (37:26 Md. R. 1788); April 4, 2011 (37:8 Md. R. 431);  April 30, 2012 (39:8 Md. R. 534); December 10, 2012 (39:24 Md. R. 1577); July 7, 2014 (41:13 Md. R. 752); February 16, 2015 (42:3 Md. R. 316); October 26, 2015 (42:21 Md. R. 1301); May 9, 2016 (43:9 Md. R. 530); February 27, 2017 (44:4 Md. R. 253); March 26, 2018 (45:6 Md. R. 319); August 26, 2019 (46:17 Md. R. 726)</annotation>
    <annotation type="History" dest="container" effective="2004-05-24">Regulation .19D amended as an emergency provision effective February 11, 2004 (31:5 Md. R. 446); amended permanently effective May 24, 2004 (31:10 Md. R. 795)</annotation>
    <annotation type="History" dest="container" effective="2018-03-26">Regulation .19D amended effective June 14, 2010 (37:12 Md. R. 800); October 26, 2015 (42:21 Md. R. 1301); February 27, 2017 (44:4 Md. R. 253); March 26, 2018 (45:6 Md. R. 319)</annotation>
    <annotation type="History" dest="container" effective="2005-04-11">Regulation .19-1 adopted as an emergency provision effective January 5, 2005 (32:6 Md. R. 634); adopted permanently effective April 11, 2005 (32:7 Md. R. 679)</annotation>
    <annotation type="History" dest="container" effective="2005-04-11">Regulation .19-3 amended as an emergency provision effective January 5, 2005 (32:6 Md. R. 634); amended permanently effective April 11, 2005 (32:7 Md. R. 679)</annotation>
    <annotation type="History" dest="container" effective="2012-04-30">Regulation .19-3 amended effective June 19, 2006 (33:12 Md. R. 997); April 9, 2007 (34:7 Md. R. 698); June 14, 2010 (37:12 Md. R. 800); April 30, 2012 (39:8 Md. R. 534)</annotation>
    <annotation type="History" dest="container" effective="2013-10-28">Regulation .19-3 repealed effective October 28, 2013 (40:21 Md. R. 1775)</annotation>
    <annotation type="History" dest="container" effective="2014-04-28">Regulation .19-3 adopted effective April 28, 2014 (41:8 Md. R. 471)</annotation>
    <annotation type="History" dest="container" effective="2009-02-23">Regulation .19-3A, B amended as an emergency provision effective November 1, 2008 (35:24 Md. R. 2069); amended permanently effective February 23, 2009 (36:4 Md. R. 353)</annotation>
    <annotation type="History" dest="container" effective="2009-10-05">Regulation .19-3A, B amended effective October 5, 2009 (36:20 Md. R. 1528)</annotation>
    <annotation type="History" dest="container" effective="2014-02-03">Regulation .19-3B amended effective December 24, 2012 (39:25 Md. R. 1613); February 3, 2014 (41:2 Md. R. 91)</annotation>
    <annotation type="History" dest="container" effective="2017-02-27">Regulation .19-3C amended effective February 27, 2017 (44:4 Md. R. 253)</annotation>
    <annotation type="History" dest="container" effective="2015-10-26">Regulation .19-3C, D amended effective October 26, 2015 (42:21 Md. R. 1301)</annotation>
    <annotation type="History" dest="container" effective="2005-12-19">Regulation .19-5 adopted effective December 19, 2005 (32:25 Md. R. 1941)</annotation>
    <annotation type="History" dest="container" effective="2018-12-31">Regulation .19-5 repealed and new Regulation .19-5 adopted effective December 31, 2018 (45:26 Md. R. 1244)</annotation>
    <annotation type="History" dest="container" effective="2015-02-16">Regulation .19-5F amended effective February 16, 2015 (42:3 Md. R. 316)</annotation>
    <annotation type="History" dest="container" effective="2010-04-19">Regulation .19-5G amended effective April 19, 2010 (37:8 Md. R. 615)</annotation>
    <annotation type="History" dest="container" effective="2015-02-16">Regulation .19-5H amended effective April 19, 2010 (37:8 Md. R. 615); February 16, 2015 (42:3 Md. R. 316)</annotation>
    <annotation type="History" dest="container" effective="2018-02-26">Regulation .20 amended effective August 8, 2011 (38:16 Md. R. 945); February 26, 2018 (45:4 Md. R. 205)</annotation>
    <annotation type="History" dest="container" effective="2005-04-11">Regulation .20A amended as an emergency provision effective January 5, 2005 (32:6 Md. R. 634); amended permanently effective April 11, 2005 (32:7 Md. R. 679)</annotation>
    <annotation type="History" dest="container" effective="2015-02-16">Regulation .20A amended effective April 10, 2006 (33:7 Md. R. 668); November 5, 2007 (34:22 Md. R. 1977); December 24, 2012 (39:25 Md. R. 1613); October 28, 2013 (40:21 Md. R. 1775); February 16, 2015 (42:3 Md. R. 316)</annotation>
    <annotation type="History" dest="container" effective="2010-04-19">Regulation .20A, B amended effective November 6, 2006 (33:22 Md. R. 1732); April 19, 2010 (37:8 Md. R. 615)</annotation>
    <annotation type="History" dest="container" effective="2014-04-28">Regulation .20A, D amended effective April 28, 2014 (41:8 Md. R. 471)</annotation>
    <annotation type="History" dest="container" effective="2008-06-30">Regulation .20B, C amended effective June 30, 2008 (35:13 Md. R. 1180)</annotation>
    <annotation type="History" dest="container" effective="2009-02-23">Regulation .20C amended as an emergency provision effective November 1, 2008 (35:24 Md. R. 2069); amended permanently effective February 23, 2009 (36:4 Md. R. 353)</annotation>
    <annotation type="History" dest="container" effective="2016-08-29">Regulation .20E adopted effective August 29, 2016 (43:17 Md. R. 955)</annotation>
    <annotation type="History" dest="container" effective="2005-04-11">Regulation .21 amended as an emergency provision effective January 5, 2005 (32:6 Md. R. 634); amended permanently effective April 11, 2005 (32:7 Md. R. 679)</annotation>
    <annotation type="History" dest="container" effective="2015-02-16">Regulation .21 amended effective February 16, 2015 (42:3 Md. R. 316)</annotation>
    <annotation type="History" dest="container" effective="2010-04-19">Regulation .21B amended effective June 19, 2006 (33:12 Md. R. 997); April 19, 2010 (37:8 Md. R. 615)</annotation>
    <annotation type="History" dest="container" effective="2005-04-11">Regulation .22 amended as an emergency provision effective January 5, 2005 (32:6 Md. R. 634); amended permanently effective April 11, 2005 (32:7 Md. R. 679)</annotation>
    <annotation type="History" dest="container" effective="2006-11-06">Regulation .22C, D amended effective November 6, 2006 (33:22 Md. R. 1732)</annotation>
    <annotation type="History" dest="container" effective="2008-06-30">Regulation .23 amended effective June 30, 2008 (35:13 Md. R. 1180)</annotation>
    <annotation type="History" dest="container" effective="2016-11-07">Regulation .23C amended effective November 7, 2016 (43:22 Md. R. 1221)</annotation>
    <annotation type="History" dest="container" effective="2009-02-23">Regulation .23D amended as an emergency provision effective November 1, 2008 (35:24 Md. R. 2069); amended permanently effective February 23, 2009 (36:4 Md. R. 353)</annotation>
    <annotation type="History" dest="container" effective="2014-04-28">Regulation .23D amended effective April 28, 2014 (41:8 Md. R. 471)</annotation>
    <annotation type="History" dest="container" effective="2009-02-23">Regulation .24 amended as an emergency provision effective November 1, 2008 (35:24 Md. R. 2069); amended permanently effective February 23, 2009 (36:4 Md. R. 353)</annotation>
    <annotation type="History" dest="container" effective="2010-04-19">Regulation .24 repealed effective April 19, 2010 (37:8 Md. R. 615)</annotation>
    <annotation type="History" dest="container" effective="2006-11-06">Regulation .25B amended effective November 6, 2006 (33:22 Md. R. 1732)</annotation>
    <annotation type="History" dest="container" effective="2008-06-30">Regulation .28 adopted effective June 30, 2008 (35:13 Md. R. 1180)</annotation>
    <annotation type="History" dest="container" effective="2012-02-06">Regulation .28 amended effective February 6, 2012 (39:2 Md. R. 141)</annotation>
    <annotation type="History" dest="container" effective="2018-02-26">Regulation .28 repealed effective February 26, 2018 (45:4 Md. R. 205)</annotation>
    <annotation type="History" dest="container" discontinuity="true" effective="2019-11-01">Chapter transferred to <cite path="|10.67.04">COMAR 10.67.04</cite> effective November 1, 2019 (46:22 Md. R. 977)</annotation>
  </annotations>
</container>
